sfdxmagic/__init__.py
sfdxmagic/functions.py
sfdxmagic/runner.py
sfdxmagic-0.0.2.dist-info/LICENSE
sfdxmagic-0.0.2.dist-info/METADATA
sfdxmagic-0.0.2.dist-info/WHEEL
sfdxmagic-0.0.2.dist-info/top_level.txt
sfdxmagic-0.0.2.dist-info/RECORD
