Metadata-Version: 2.1
Name: sfdxmagic
Version: 0.0.2
Summary: Execute cells with SOQL and APEX within Jupyter notebooks
Home-page: UNKNOWN
Author: Daniele Piccone
Author-email: mild.taste@gmail.com
License: UNKNOWN
Keywords: soql,jupyter,salesforce,apex
Platform: UNKNOWN
Requires-Dist: jupyterlab
Requires-Dist: pandas
